greykite/__init__.py
greykite/algo/__init__.py
greykite/algo/changepoint/__init__.py
greykite/algo/changepoint/adalasso/__init__.py
greykite/algo/changepoint/adalasso/auto_changepoint_params.py
greykite/algo/changepoint/adalasso/changepoint_detector.py
greykite/algo/changepoint/adalasso/changepoints_utils.py
greykite/algo/changepoint/shift_detection/__init__.py
greykite/algo/changepoint/shift_detection/shift_detector.py
greykite/algo/common/__init__.py
greykite/algo/common/col_name_utils.py
greykite/algo/common/forecast_one_by_one.py
greykite/algo/common/holiday_grouper.py
greykite/algo/common/holiday_inferrer.py
greykite/algo/common/holiday_utils.py
greykite/algo/common/l1_quantile_regression.py
greykite/algo/common/ml_models.py
greykite/algo/common/model_summary.py
greykite/algo/common/model_summary_utils.py
greykite/algo/common/partial_regularize_regression.py
greykite/algo/common/seasonality_inferrer.py
greykite/algo/forecast/__init__.py
greykite/algo/forecast/silverkite/__init__.py
greykite/algo/forecast/silverkite/auto_config.py
greykite/algo/forecast/silverkite/forecast_silverkite.py
greykite/algo/forecast/silverkite/forecast_silverkite_helper.py
greykite/algo/forecast/silverkite/forecast_simple_silverkite.py
greykite/algo/forecast/silverkite/forecast_simple_silverkite_helper.py
greykite/algo/forecast/silverkite/constants/__init__.py
greykite/algo/forecast/silverkite/constants/silverkite_column.py
greykite/algo/forecast/silverkite/constants/silverkite_component.py
greykite/algo/forecast/silverkite/constants/silverkite_constant.py
greykite/algo/forecast/silverkite/constants/silverkite_holiday.py
greykite/algo/forecast/silverkite/constants/silverkite_seasonality.py
greykite/algo/forecast/silverkite/constants/silverkite_time_frequency.py
greykite/algo/forecast/similarity/__init__.py
greykite/algo/forecast/similarity/forecast_similarity_based.py
greykite/algo/reconcile/__init__.py
greykite/algo/reconcile/hierarchical_relationship.py
greykite-1.0.0.dist-info/AUTHORS.rst
greykite-1.0.0.dist-info/LICENSE
greykite-1.0.0.dist-info/METADATA
greykite-1.0.0.dist-info/WHEEL
greykite-1.0.0.dist-info/entry_points.txt
greykite-1.0.0.dist-info/top_level.txt
greykite-1.0.0.dist-info/RECORD
