Metadata-Version: 2.1
Name: greykite
Version: 1.0.0
Summary: A python package for flexible forecasting
Home-page: https://github.com/linkedin/greykite
Author: R. Hosseini, A. Chen, K. Yang, S. Patra, Y. Su, R. Arora
Author-email: reza1317@gmail.com
License: BSD-2-CLAUSE
Keywords: greykite
Platform: UNKNOWN
Classifier: Development Status :: 2 - Pre-Alpha
Classifier: Intended Audience :: Developers
Classifier: License :: OSI Approved :: BSD License
Classifier: Natural Language :: English
Classifier: Programming Language :: Python :: 3.10
Requires-Python: >=3.10
License-File: LICENSE
License-File: AUTHORS.rst
Requires-Dist: cvxpy >=1.2.1
Requires-Dist: dill >=0.3.1.1
Requires-Dist: holidays <0.25
Requires-Dist: holidays-ext >=0.0.7
Requires-Dist: ipython >=7.31.1
Requires-Dist: matplotlib >=3.4.1
Requires-Dist: numpy <1.25.0,>=1.22.0
Requires-Dist: osqp >=0.6.2
Requires-Dist: overrides >=2.8.0
Requires-Dist: pandas <2.0.0,>=1.5.0
Requires-Dist: patsy >=0.5.1
Requires-Dist: plotly >=4.12.0
Requires-Dist: pmdarima <=1.8.5,>=1.8.0
Requires-Dist: pytest >=4.6.5
Requires-Dist: pytest-runner >=5.1
Requires-Dist: scipy <1.11.0,>=1.5.4
Requires-Dist: six >=1.15.0
Requires-Dist: scikit-learn >=0.24.1
Requires-Dist: statsmodels >=0.12.2
Requires-Dist: testfixtures >=6.14.2
Requires-Dist: tqdm >=4.52.0
